src/__init__.py
src/example.py
src/log_ex.py
log_ex_simple-0.1.dist-info/LICENSE
log_ex_simple-0.1.dist-info/METADATA
log_ex_simple-0.1.dist-info/WHEEL
log_ex_simple-0.1.dist-info/top_level.txt
log_ex_simple-0.1.dist-info/RECORD
