Metadata-Version: 2.1
Name: log_ex_simple
Version: 0.1
Summary: A simple logging function to log messages to the screen or to a file.
Home-page: https://github.com/stoday/log_ex
Author: Yadots
Author-email: stoday@gmail.com
Classifier: Programming Language :: Python :: 3
Classifier: License :: OSI Approved :: MIT License
Classifier: Operating System :: OS Independent
Requires-Python: >=3.9
License-File: LICENSE
